peerpkg/__init__.py
peerpkg-1.9.dist-info/LICENSE
peerpkg-1.9.dist-info/METADATA
peerpkg-1.9.dist-info/WHEEL
peerpkg-1.9.dist-info/entry_points.txt
peerpkg-1.9.dist-info/top_level.txt
peerpkg-1.9.dist-info/RECORD
