Metadata-Version: 2.1
Name: peerpkg
Version: 1.9
Summary: # peer
Home-page: https://github.com/ahmedgirach/peer
Author: Ahmed Girach
Author-email: ahmed@peerbits.com
License: MIT
Platform: UNKNOWN
